README.md
setup.py
ledshimdemo/__init__.py
ledshimdemo/__main__.py
ledshimdemo/abstract_effect.py
ledshimdemo/canvas.py
ledshimdemo/colours.py
ledshimdemo/configure_logging.py
ledshimdemo/display_options.py
ledshimdemo/effect_cache.py
ledshimdemo/effect_controller.py
ledshimdemo/effect_parade.py
ledshimdemo/effect_publisher.py
ledshimdemo/effect_subscriber.py
ledshimdemo/ipaddress_param.py
ledshimdemo/pixel.py
ledshimdemo.egg-info/PKG-INFO
ledshimdemo.egg-info/SOURCES.txt
ledshimdemo.egg-info/dependency_links.txt
ledshimdemo.egg-info/entry_points.txt
ledshimdemo.egg-info/requires.txt
ledshimdemo.egg-info/top_level.txt
ledshimdemo/effects/__init__.py
ledshimdemo/effects/binary_clock.py
ledshimdemo/effects/candle.py
ledshimdemo/effects/cheerlights.py
ledshimdemo/effects/coloured_lights.py
ledshimdemo/effects/digital_rain.py
ledshimdemo/effects/gradient_graph.py
ledshimdemo/effects/rainbow.py
ledshimdemo/effects/random_blink.py
ledshimdemo/effects/solid_colours.py
tests/effects/__init__.py
tests/effects/not_an_effect.py
tests/effects/test_binary_clock.py
tests/effects/test_candle.py
tests/effects/test_cheerlights.py
tests/effects/test_coloured_lights.py
tests/effects/test_digital_rain.py
tests/effects/test_gradient_graph.py
tests/effects/test_rainbow.py
tests/effects/test_random_blink.py
tests/effects/test_solid_colours.py
tests/test_effects/__init__.py
tests/test_effects/dummy1_effect.py
tests/test_effects/dummy2_effect.py
tests/test_effects/dummy3_effect.py