Metadata-Version: 2.1
Name: ledshimdemo
Version: 2.0.0
Summary: Show various effects on a Pimoroni LED shim.
Home-page: https://github.com/RatJuggler/led-shim-demo
Author: John Chase
Author-email: ratteal@gmail.com
License: MIT
Platform: UNKNOWN
Classifier: License :: OSI Approved :: MIT License
Classifier: Development Status :: 5 - Production/Stable
Classifier: Programming Language :: Python :: 3.5
Classifier: Operating System :: POSIX :: Linux
Classifier: Topic :: System :: Hardware
Requires-Python: >=3.5.3
